rustc_dev_t_x64_win_msvc_nightly_p3/__init__.py
rustc_dev_t_x64_win_msvc_nightly_p3/data/derive_where-06dd06218cd036c9.dll.lib
rustc_dev_t_x64_win_msvc_nightly_p3/data/displaydoc-e6bf581cd9edd608.dll.lib
rustc_dev_t_x64_win_msvc_nightly_p3/data/libaho_corasick-c633c9e6ab268a91.rmeta
rustc_dev_t_x64_win_msvc_nightly_p3/data/libarrayvec-e63abb4824851eb5.rmeta
rustc_dev_t_x64_win_msvc_nightly_p3/data/libcc-ac3b48dd0b88c923.rmeta
rustc_dev_t_x64_win_msvc_nightly_p3/data/libcrossbeam_epoch-6712f73477d6dd36.rmeta
rustc_dev_t_x64_win_msvc_nightly_p3/data/libequivalent-471f3bef1ffc8e4b.rmeta
rustc_dev_t_x64_win_msvc_nightly_p3/data/libfluent_syntax-761e209b7e857e33.rmeta
rustc_dev_t_x64_win_msvc_nightly_p3/data/libicu_locid_transform_data-c481bd3a17a684b9.rmeta
rustc_dev_t_x64_win_msvc_nightly_p3/data/liboverload-22f8d56e12ac0860.rmeta
rustc_dev_t_x64_win_msvc_nightly_p3/data/libpunycode-fdfaeb69b16895aa.rmeta
rustc_dev_t_x64_win_msvc_nightly_p3/data/librand-030fdd51f419520f.rmeta
rustc_dev_t_x64_win_msvc_nightly_p3/data/librustc_ast-b5ea6b0830fdb99a.rmeta
rustc_dev_t_x64_win_msvc_nightly_p3/data/librustc_codegen_ssa-eb76c7ecbc000784.rmeta
rustc_dev_t_x64_win_msvc_nightly_p3/data/librustc_const_eval-c5e1595c12c08aad.rmeta
rustc_dev_t_x64_win_msvc_nightly_p3/data/librustc_fs_util-009f567324386514.rmeta
rustc_dev_t_x64_win_msvc_nightly_p3/data/librustc_hash-079b2d63ac15c38b.rmeta
rustc_dev_t_x64_win_msvc_nightly_p3/data/librustc_hir_analysis-6e76db0eec74f5fd.rmeta
rustc_dev_t_x64_win_msvc_nightly_p3/data/librustc_log-9898b3478a3a22e9.rmeta
rustc_dev_t_x64_win_msvc_nightly_p3/data/librustc_monomorphize-eee2506623c2f5b6.rmeta
rustc_dev_t_x64_win_msvc_nightly_p3/data/librustc_passes-8f26dbe20531a90d.rmeta
rustc_dev_t_x64_win_msvc_nightly_p3/data/libsha1-9947827a717f1a00.rmeta
rustc_dev_t_x64_win_msvc_nightly_p3/data/libunicode_normalization-b4822d9e9ec20021.rmeta
rustc_dev_t_x64_win_msvc_nightly_p3/data/libunicode_width-9b7b31d536889eec.rmeta
rustc_dev_t_x64_win_msvc_nightly_p3-1.91.0.dist-info/METADATA
rustc_dev_t_x64_win_msvc_nightly_p3-1.91.0.dist-info/WHEEL
rustc_dev_t_x64_win_msvc_nightly_p3-1.91.0.dist-info/top_level.txt
rustc_dev_t_x64_win_msvc_nightly_p3-1.91.0.dist-info/RECORD
