Metadata-Version: 2.4
Name: rustc_dev_t_x64_win_msvc_nightly_p3
Version: 1.91.0
Summary: Segment rustc-dev.target.x86_64-pc-windows-msvc part p3
License: MIT
